memail
