Metadata-Version: 1.0
Name: memail
Version: 0.71
Summary: Personalized Email Project for COS518
Home-page: http://github.com/nicholasturner1/cos518
Author: Nicholas Turner, Yuanzhi Li, Paul Jackson
Author-email: nturner.stanford@gmail.com
License: MIT
Platform: UNKNOWN
